estoverlap/__init__.py
estoverlap/estoverlap.py
estoverlap/version.py
estoverlap/overlap_utils/__init__.py
estoverlap/overlap_utils/uniform_synchronous.py
estoverlap-0.0.1.dist-info/LICENSE.txt
estoverlap-0.0.1.dist-info/METADATA
estoverlap-0.0.1.dist-info/WHEEL
estoverlap-0.0.1.dist-info/top_level.txt
estoverlap-0.0.1.dist-info/RECORD
