Metadata-Version: 2.1
Name: estoverlap
Version: 0.0.1
Summary: Parameter estimation from overlapping observations.
Home-page: https://currently.not.available
Author: Michael A. Clayton Consulting Inc.
Author-email: michael.clayton@sympatico.ca
License: MIT
Keywords: parameter estimation,overlapping observations
Platform: UNKNOWN
Classifier: Programming Language :: Python :: 3
Classifier: License :: OSI Approved :: MIT License
Classifier: Operating System :: OS Independent
Classifier: Intended Audience :: Financial and Insurance Industry
Classifier: Development Status :: 3 - Alpha
Requires-Python: >=3.7
License-File: LICENSE.txt
Requires-Dist: numpy (!=1.19.4,>=1.19)
Requires-Dist: pandas (>=1.1)
Requires-Dist: scipy (>=1.5)
